zlsnasdisplay/__init__.py
zlsnasdisplay/__main__.py
zlsnasdisplay/_version.py
zlsnasdisplay/display_controller.py
zlsnasdisplay/display_renderer.py
zlsnasdisplay/fonts/MaterialSymbolsRounded.ttf
zlsnasdisplay/fonts/Ubuntu-Light.ttf
zlsnasdisplay/fonts/Ubuntu-Regular.ttf
zlsnasdisplay/main.py
zlsnasdisplay/network_operations.py
zlsnasdisplay/py.typed
zlsnasdisplay/system_operations.py
zlsnasdisplay/waveshare_epd/__init__.py
zlsnasdisplay/waveshare_epd/epd2in9_V2.py
zlsnasdisplay/waveshare_epd/epdconfig.py
zlsnasdisplay-2.0.3.dist-info/LICENSE
zlsnasdisplay-2.0.3.dist-info/METADATA
zlsnasdisplay-2.0.3.dist-info/WHEEL
zlsnasdisplay-2.0.3.dist-info/entry_points.txt
zlsnasdisplay-2.0.3.dist-info/RECORD
