Metadata-Version: 2.3
Name: zlsnasdisplay
Version: 2.0.3
Summary: Eink display manager
License: MIT
Author: Ondrej Zalesky
Author-email: o.zalesky@gmail.com
Requires-Python: >=3.9,<4.0
Classifier: License :: OSI Approved :: MIT License
Classifier: Programming Language :: Python :: 3
Classifier: Programming Language :: Python :: 3.9
Classifier: Programming Language :: Python :: 3.10
Classifier: Programming Language :: Python :: 3.11
Classifier: Programming Language :: Python :: 3.12
Classifier: Programming Language :: Python :: 3.13
Requires-Dist: gpiozero (>=2.0.1,<3.0.0)
Requires-Dist: pillow (>=10.2,<12.0)
Requires-Dist: psutil (>=5.9.8,<7.0.0)
Requires-Dist: requests (>=2.31.0,<3.0.0)
Requires-Dist: schedule (>=1.2.1,<2.0.0)
Requires-Dist: spidev (>=3.7,<4.0)
